cnpj_cd/__init__.py
cnpj_cd/cnpj_check_digits.py
cnpj_cd/exceptions.py
cnpj_cd-1.0.2.dist-info/licenses/LICENSE
cnpj_cd-1.0.2.dist-info/METADATA
cnpj_cd-1.0.2.dist-info/WHEEL
cnpj_cd-1.0.2.dist-info/top_level.txt
cnpj_cd-1.0.2.dist-info/RECORD
